{"trial_id": "07", "hyperparameters": {"space": [{"class_name": "Int", "config": {"name": "units", "default": null, "conditions": [], "min_value": 32, "max_value": 512, "step": 32, "sampling": "linear"}}, {"class_name": "Choice", "config": {"name": "l2", "default": 0.01, "conditions": [], "values": [0.01, 0.001, 0.0001], "ordered": true}}, {"class_name": "Choice", "config": {"name": "learning_rate", "default": 0.01, "conditions": [], "values": [0.01, 0.001, 0.0001], "ordered": true}}], "values": {"units": 288, "l2": 0.001, "learning_rate": 0.001}}, "metrics": {"metrics": {"loss": {"direction": "min", "observations": [{"value": [272478643814.4], "step": 13}]}, "mae": {"direction": "min", "observations": [{"value": [296266.2875], "step": 13}]}, "val_loss": {"direction": "min", "observations": [{"value": [84076308070.4], "step": 13}]}, "val_mae": {"direction": "min", "observations": [{"value": [211866.7375], "step": 13}]}}}, "score": 296266.2875, "best_step": 13, "status": "COMPLETED", "message": null}